<?xml version="1.0" encoding="utf-8"?>
<INVOICE>
  <Product>
    <Ln.>1</Ln.>
    <PO>19_03_09-1-3</PO>
    <ProductCode>1-3-PCB-01-2</ProductCode>
    <Description></Description>
    <Qty>1</Qty>
    <UnitPrice>0.000</UnitPrice>
    <Amount>0.00</Amount>
  </Product>
  <Product>
    <Ln.>2</Ln.>
    <PO>19_03_09-1-3</PO>
    <ProductCode>1-3-PCB-21-362</ProductCode>
    <Description></Description>
    <Qty>1</Qty>
    <UnitPrice>0.000</UnitPrice>
    <Amount>0.00</Amount>
  </Product>
  <Product>
    <Ln.>3</Ln.>
    <PO>19_03_09-1-3</PO>
    <ProductCode>1-3-PCB-12R-209</ProductCode>
    <Description></Description>
    <Qty>1</Qty>
    <UnitPrice>0.000</UnitPrice>
    <Amount>0.00</Amount>
  </Product>
  <Product>
    <Ln.>4</Ln.>
    <PO>19_03_09-1-3</PO>
    <ProductCode>1-3-PCB-11-182</ProductCode>
    <Description></Description>
    <Qty>1</Qty>
    <UnitPrice>0.000</UnitPrice>
    <Amount>0.00</Amount>
  </Product>
  <Product>
    <Ln.>5</Ln.>
    <PO>19_03_09-1-3</PO>
    <ProductCode>1-3-PCB-12-200</ProductCode>
    <Description></Description>
    <Qty>1</Qty>
    <UnitPrice>0.000</UnitPrice>
    <Amount>0.00</Amount>
  </Product>
  <Product>
    <Ln.>6</Ln.>
    <PO>19_03_09-1-3</PO>
    <ProductCode>1-3-PCB-11R-191</ProductCode>
    <Description></Description>
    <Qty>1</Qty>
    <UnitPrice>0.000</UnitPrice>
    <Amount>0.00</Amount>
  </Product>
  <Product>
    <Ln.>7</Ln.>
    <PO>19_03_09-1-3</PO>
    <ProductCode>1-3-PCB-22-380</ProductCode>
    <Description></Description>
    <Qty>1</Qty>
    <UnitPrice>0.000</UnitPrice>
    <Amount>0.00</Amount>
  </Product>
  <Product>
    <Ln.>8</Ln.>
    <PO>19_03_09-1-3</PO>
    <ProductCode>1-3-PCB-10-164</ProductCode>
    <Description></Description>
    <Qty>1</Qty>
    <UnitPrice>0.000</UnitPrice>
    <Amount>0.00</Amount>
  </Product>
  <Product>
    <Ln.>9</Ln.>
    <PO>19_03_09-1-3</PO>
    <ProductCode>1-3-PCB-10R-173</ProductCode>
    <Description></Description>
    <Qty>1</Qty>
    <UnitPrice>0.000</UnitPrice>
    <Amount>0.00</Amount>
  </Product>
  <Product>
    <Ln.>10</Ln.>
    <PO>19_03_09-1-3</PO>
    <ProductCode>1-3-PCB-08-128</ProductCode>
    <Description></Description>
    <Qty>1</Qty>
    <UnitPrice>0.000</UnitPrice>
    <Amount>0.00</Amount>
  </Product>
  <Product>
    <Ln.>11</Ln.>
    <PO>19_03_09-1-3</PO>
    <ProductCode>1-3-PCB-08R-137</ProductCode>
    <Description></Description>
    <Qty>1</Qty>
    <UnitPrice>0.000</UnitPrice>
    <Amount>0.00</Amount>
  </Product>
  <Product>
    <Ln.>12</Ln.>
    <PO>19_03_09-1-3</PO>
    <ProductCode>1-3-PCB-03-38</ProductCode>
    <Description></Description>
    <Qty>1</Qty>
    <UnitPrice>0.000</UnitPrice>
    <Amount>0.00</Amount>
  </Product>
  <Product>
    <Ln.>13</Ln.>
    <PO>19_03_09-1-3</PO>
    <ProductCode>1-3-PCB-03R-47</ProductCode>
    <Description></Description>
    <Qty>1</Qty>
    <UnitPrice>0.000</UnitPrice>
    <Amount>0.00</Amount>
  </Product>
  <Product>
    <Ln.>14</Ln.>
    <PO>19_03_09-1-3</PO>
    <ProductCode>1-3-PCB-23R-407</ProductCode>
    <Description></Description>
    <Qty>1</Qty>
    <UnitPrice>0.000</UnitPrice>
    <Amount>0.00</Amount>
  </Product>
  <Product>
    <Ln.>15</Ln.>
    <PO>19_03_09-1-3</PO>
    <ProductCode>1-3-PCB-23-398</ProductCode>
    <Description></Description>
    <Qty>1</Qty>
    <UnitPrice>0.000</UnitPrice>
    <Amount>0.00</Amount>
  </Product>
  <Product>
    <Ln.>16</Ln.>
    <PO>19_03_09-1-3</PO>
    <ProductCode>1-3-PCB-13-218</ProductCode>
    <Description></Description>
    <Qty>1</Qty>
    <UnitPrice>0.000</UnitPrice>
    <Amount>0.00</Amount>
  </Product>
  <Product>
    <Ln.>17</Ln.>
    <PO>19_03_09-1-3</PO>
    <ProductCode>1-3-PCB-15R-263</ProductCode>
    <Description></Description>
    <Qty>1</Qty>
    <UnitPrice>0.000</UnitPrice>
    <Amount>0.00</Amount>
  </Product>
  <Product>
    <Ln.>18</Ln.>
    <PO>19_03_09-1-3</PO>
    <ProductCode>1-3-PCB-14R-245</ProductCode>
    <Description></Description>
    <Qty>1</Qty>
    <UnitPrice>0.000</UnitPrice>
    <Amount>0.00</Amount>
  </Product>
  <Product>
    <Ln.>19</Ln.>
    <PO>19_03_09-1-3</PO>
    <ProductCode>1-3-PCB-14-236</ProductCode>
    <Description></Description>
    <Qty>1</Qty>
    <UnitPrice>0.000</UnitPrice>
    <Amount>0.00</Amount>
  </Product>
  <Product>
    <Ln.>20</Ln.>
    <PO>19_03_09-1-3</PO>
    <ProductCode>1-3-PCB-15-254</ProductCode>
    <Description></Description>
    <Qty>1</Qty>
    <UnitPrice>0.000</UnitPrice>
    <Amount>0.00</Amount>
  </Product>
  <Product>
    <Ln.>21</Ln.>
    <PO>19_03_09-1-3</PO>
    <ProductCode>1-3-PCB-09R-155</ProductCode>
    <Description></Description>
    <Qty>1</Qty>
    <UnitPrice>0.000</UnitPrice>
    <Amount>0.00</Amount>
  </Product>
  <Product>
    <Ln.>22</Ln.>
    <PO>19_03_09-1-3</PO>
    <ProductCode>1-3-PCB-22R-389</ProductCode>
    <Description></Description>
    <Qty>1</Qty>
    <UnitPrice>0.000</UnitPrice>
    <Amount>0.00</Amount>
  </Product>
</INVOICE>
