<?xml version="1.0" encoding="utf-8"?>
<INVOICE>
  <Product>
    <Ln.>1</Ln.>
    <PO>2018_3_07-14-12</PO>
    <ProductCode>14-12-WGQ11-179</ProductCode>
    <Description></Description>
    <Qty>1</Qty>
    <UnitPrice>0.000</UnitPrice>
    <Amount>0.00</Amount>
  </Product>
  <Product>
    <Ln.>2</Ln.>
    <PO>2018_3_07-14-12</PO>
    <ProductCode>14-12-WGQ1-259</ProductCode>
    <Description></Description>
    <Qty>1</Qty>
    <UnitPrice>0.000</UnitPrice>
    <Amount>0.00</Amount>
  </Product>
  <Product>
    <Ln.>3</Ln.>
    <PO>2018_3_07-14-12</PO>
    <ProductCode>14-12-WGQ13-211</ProductCode>
    <Description></Description>
    <Qty>1</Qty>
    <UnitPrice>0.000</UnitPrice>
    <Amount>0.00</Amount>
  </Product>
  <Product>
    <Ln.>4</Ln.>
    <PO>2018_3_07-14-12</PO>
    <ProductCode>14-12-WGQ18-243</ProductCode>
    <Description></Description>
    <Qty>1</Qty>
    <UnitPrice>0.000</UnitPrice>
    <Amount>0.00</Amount>
  </Product>
  <Product>
    <Ln.>5</Ln.>
    <PO>2018_3_07-14-12</PO>
    <ProductCode>14-12-WGQ12-195</ProductCode>
    <Description></Description>
    <Qty>1</Qty>
    <UnitPrice>0.000</UnitPrice>
    <Amount>0.00</Amount>
  </Product>
  <Product>
    <Ln.>6</Ln.>
    <PO>2018_3_07-14-12</PO>
    <ProductCode>14-12-WGQ15-227</ProductCode>
    <Description></Description>
    <Qty>1</Qty>
    <UnitPrice>0.000</UnitPrice>
    <Amount>0.00</Amount>
  </Product>
  <Product>
    <Ln.>7</Ln.>
    <PO>2018_3_07-14-12</PO>
    <ProductCode>14-12-WGQ6-275</ProductCode>
    <Description></Description>
    <Qty>1</Qty>
    <UnitPrice>0.000</UnitPrice>
    <Amount>0.00</Amount>
  </Product>
</INVOICE>
