<?xml version="1.0" encoding="utf-8"?>
<INVOICE>
  <Product>
    <Ln.>1</Ln.>
    <PO>19_03_19-16-9</PO>
    <ProductCode>16-9-YDB13L-1004</ProductCode>
    <Description></Description>
    <Qty>1</Qty>
    <UnitPrice>0.000</UnitPrice>
    <Amount>0.00</Amount>
  </Product>
  <Product>
    <Ln.>2</Ln.>
    <PO>19_03_19-16-6</PO>
    <ProductCode>16-6-YDB12M-1016</ProductCode>
    <Description></Description>
    <Qty>1</Qty>
    <UnitPrice>0.000</UnitPrice>
    <Amount>0.00</Amount>
  </Product>
  <Product>
    <Ln.>3</Ln.>
    <PO>19_03_19-16-6</PO>
    <ProductCode>16-6-YDB12R-1030</ProductCode>
    <Description></Description>
    <Qty>1</Qty>
    <UnitPrice>0.000</UnitPrice>
    <Amount>0.00</Amount>
  </Product>
  <Product>
    <Ln.>4</Ln.>
    <PO>19_03_19-16-8</PO>
    <ProductCode>16-8-YDB26L-1047</ProductCode>
    <Description></Description>
    <Qty>1</Qty>
    <UnitPrice>0.000</UnitPrice>
    <Amount>0.00</Amount>
  </Product>
  <Product>
    <Ln.>5</Ln.>
    <PO>19_03_19-16-6</PO>
    <ProductCode>16-6-YDB25M-1060</ProductCode>
    <Description></Description>
    <Qty>1</Qty>
    <UnitPrice>0.000</UnitPrice>
    <Amount>0.00</Amount>
  </Product>
  <Product>
    <Ln.>6</Ln.>
    <PO>19_03_19-16-6</PO>
    <ProductCode>16-6-YDB25R-1074</ProductCode>
    <Description></Description>
    <Qty>1</Qty>
    <UnitPrice>0.000</UnitPrice>
    <Amount>0.00</Amount>
  </Product>
  <Product>
    <Ln.>7</Ln.>
    <PO>19_03_19-16-9</PO>
    <ProductCode>16-9-YDB21R-1121</ProductCode>
    <Description></Description>
    <Qty>1</Qty>
    <UnitPrice>0.000</UnitPrice>
    <Amount>0.00</Amount>
  </Product>
  <Product>
    <Ln.>8</Ln.>
    <PO>19_03_19-16-6</PO>
    <ProductCode>16-6-YDB22R-1132</ProductCode>
    <Description></Description>
    <Qty>1</Qty>
    <UnitPrice>0.000</UnitPrice>
    <Amount>0.00</Amount>
  </Product>
  <Product>
    <Ln.>9</Ln.>
    <PO>19_03_19-16-6</PO>
    <ProductCode>16-6-YDB4M-18</ProductCode>
    <Description></Description>
    <Qty>1</Qty>
    <UnitPrice>0.000</UnitPrice>
    <Amount>0.00</Amount>
  </Product>
  <Product>
    <Ln.>10</Ln.>
    <PO>19_03_19-16-6</PO>
    <ProductCode>16-6-YDB21L-33</ProductCode>
    <Description></Description>
    <Qty>1</Qty>
    <UnitPrice>0.000</UnitPrice>
    <Amount>0.00</Amount>
  </Product>
  <Product>
    <Ln.>11</Ln.>
    <PO>19_03_19-16-7</PO>
    <ProductCode>16-7-YDB22L-49</ProductCode>
    <Description></Description>
    <Qty>1</Qty>
    <UnitPrice>0.000</UnitPrice>
    <Amount>0.00</Amount>
  </Product>
  <Product>
    <Ln.>12</Ln.>
    <PO>19_03_19-16-8</PO>
    <ProductCode>16-8-YDB13R-79</ProductCode>
    <Description></Description>
    <Qty>1</Qty>
    <UnitPrice>0.000</UnitPrice>
    <Amount>0.00</Amount>
  </Product>
  <Product>
    <Ln.>13</Ln.>
    <PO>19_03_19-16-4</PO>
    <ProductCode>16-4-YDB13M-90</ProductCode>
    <Description></Description>
    <Qty>1</Qty>
    <UnitPrice>0.000</UnitPrice>
    <Amount>0.00</Amount>
  </Product>
  <Product>
    <Ln.>14</Ln.>
    <PO>19_03_19-16-6</PO>
    <ProductCode>16-6-YDB25L-107</ProductCode>
    <Description></Description>
    <Qty>1</Qty>
    <UnitPrice>0.000</UnitPrice>
    <Amount>0.00</Amount>
  </Product>
  <Product>
    <Ln.>15</Ln.>
    <PO>19_03_19-16-6</PO>
    <ProductCode>16-6-YDB26M-136</ProductCode>
    <Description></Description>
    <Qty>1</Qty>
    <UnitPrice>0.000</UnitPrice>
    <Amount>0.00</Amount>
  </Product>
  <Product>
    <Ln.>16</Ln.>
    <PO>19_03_19-16-8</PO>
    <ProductCode>16-8-YDB15R-167</ProductCode>
    <Description></Description>
    <Qty>1</Qty>
    <UnitPrice>0.000</UnitPrice>
    <Amount>0.00</Amount>
  </Product>
  <Product>
    <Ln.>17</Ln.>
    <PO>19_03_19-16-8</PO>
    <ProductCode>16-8-YDB14R-211</ProductCode>
    <Description></Description>
    <Qty>1</Qty>
    <UnitPrice>0.000</UnitPrice>
    <Amount>0.00</Amount>
  </Product>
  <Product>
    <Ln.>18</Ln.>
    <PO>19_03_19-16-8</PO>
    <ProductCode>16-8-YDB18R-343</ProductCode>
    <Description></Description>
    <Qty>1</Qty>
    <UnitPrice>0.000</UnitPrice>
    <Amount>0.00</Amount>
  </Product>
  <Product>
    <Ln.>19</Ln.>
    <PO>19_03_19-16-8</PO>
    <ProductCode>16-8-YDB19R-387</ProductCode>
    <Description></Description>
    <Qty>1</Qty>
    <UnitPrice>0.000</UnitPrice>
    <Amount>0.00</Amount>
  </Product>
  <Product>
    <Ln.>20</Ln.>
    <PO>19_03_19-16-6</PO>
    <ProductCode>16-6-YDB20R-429</ProductCode>
    <Description></Description>
    <Qty>1</Qty>
    <UnitPrice>0.000</UnitPrice>
    <Amount>0.00</Amount>
  </Product>
  <Product>
    <Ln.>21</Ln.>
    <PO>19_03_19-16-7</PO>
    <ProductCode>16-7-YDB4L-475</ProductCode>
    <Description></Description>
    <Qty>1</Qty>
    <UnitPrice>0.000</UnitPrice>
    <Amount>0.00</Amount>
  </Product>
  <Product>
    <Ln.>22</Ln.>
    <PO>19_03_19-16-8</PO>
    <ProductCode>16-8-YDB24R-490</ProductCode>
    <Description></Description>
    <Qty>1</Qty>
    <UnitPrice>0.000</UnitPrice>
    <Amount>0.00</Amount>
  </Product>
  <Product>
    <Ln.>23</Ln.>
    <PO>19_03_19-16-8</PO>
    <ProductCode>16-8-YDB1M-579</ProductCode>
    <Description></Description>
    <Qty>1</Qty>
    <UnitPrice>0.000</UnitPrice>
    <Amount>0.00</Amount>
  </Product>
  <Product>
    <Ln.>24</Ln.>
    <PO>19_03_19-16-8</PO>
    <ProductCode>16-8-YDB4R-680</ProductCode>
    <Description></Description>
    <Qty>1</Qty>
    <UnitPrice>0.000</UnitPrice>
    <Amount>0.00</Amount>
  </Product>
  <Product>
    <Ln.>25</Ln.>
    <PO>19_03_19-16-8</PO>
    <ProductCode>16-8-YDB7R-694</ProductCode>
    <Description></Description>
    <Qty>1</Qty>
    <UnitPrice>0.000</UnitPrice>
    <Amount>0.00</Amount>
  </Product>
  <Product>
    <Ln.>26</Ln.>
    <PO>19_03_19-16-7</PO>
    <ProductCode>16-7-YDB6M-752</ProductCode>
    <Description></Description>
    <Qty>1</Qty>
    <UnitPrice>0.000</UnitPrice>
    <Amount>0.00</Amount>
  </Product>
  <Product>
    <Ln.>27</Ln.>
    <PO>19_03_19-16-7</PO>
    <ProductCode>16-7-YDB5M-796</ProductCode>
    <Description></Description>
    <Qty>1</Qty>
    <UnitPrice>0.000</UnitPrice>
    <Amount>0.00</Amount>
  </Product>
  <Product>
    <Ln.>28</Ln.>
    <PO>19_03_19-16-7</PO>
    <ProductCode>16-7-YDB11R-957</ProductCode>
    <Description></Description>
    <Qty>1</Qty>
    <UnitPrice>0.000</UnitPrice>
    <Amount>0.00</Amount>
  </Product>
  <Product>
    <Ln.>29</Ln.>
    <PO>19_03_19-16-4</PO>
    <ProductCode>16-4-YDB11M-969</ProductCode>
    <Description></Description>
    <Qty>1</Qty>
    <UnitPrice>0.000</UnitPrice>
    <Amount>0.00</Amount>
  </Product>
  <Product>
    <Ln.>30</Ln.>
    <PO>19_03_19-16-4</PO>
    <ProductCode>16-4-YDB14L-984</ProductCode>
    <Description></Description>
    <Qty>1</Qty>
    <UnitPrice>0.000</UnitPrice>
    <Amount>0.00</Amount>
  </Product>
</INVOICE>
