<?xml version="1.0" encoding="utf-8"?>
<INVOICE>
  <Product>
    <Ln.>1</Ln.>
    <PO>18_12_17-4-4</PO>
    <ProductCode>4-4-PCYB14L-201</ProductCode>
    <Description></Description>
    <Qty>1</Qty>
    <UnitPrice>0.000</UnitPrice>
    <Amount>0.00</Amount>
  </Product>
  <Product>
    <Ln.>2</Ln.>
    <PO>18_12_17-4-4</PO>
    <ProductCode>4-4-PCYB07L-68</ProductCode>
    <Description></Description>
    <Qty>1</Qty>
    <UnitPrice>0.000</UnitPrice>
    <Amount>0.00</Amount>
  </Product>
  <Product>
    <Ln.>3</Ln.>
    <PO>18_12_17-4-4</PO>
    <ProductCode>4-4-PCYB07L-53</ProductCode>
    <Description></Description>
    <Qty>1</Qty>
    <UnitPrice>0.000</UnitPrice>
    <Amount>0.00</Amount>
  </Product>
  <Product>
    <Ln.>4</Ln.>
    <PO>18_12_17-4-4</PO>
    <ProductCode>4-4-PCYB06L-48</ProductCode>
    <Description></Description>
    <Qty>1</Qty>
    <UnitPrice>0.000</UnitPrice>
    <Amount>0.00</Amount>
  </Product>
  <Product>
    <Ln.>5</Ln.>
    <PO>18_12_17-4-4</PO>
    <ProductCode>4-4-PCYB06L-63</ProductCode>
    <Description></Description>
    <Qty>1</Qty>
    <UnitPrice>0.000</UnitPrice>
    <Amount>0.00</Amount>
  </Product>
  <Product>
    <Ln.>6</Ln.>
    <PO>18_12_17-4-4</PO>
    <ProductCode>4-4-PCYB05L-43</ProductCode>
    <Description></Description>
    <Qty>1</Qty>
    <UnitPrice>0.000</UnitPrice>
    <Amount>0.00</Amount>
  </Product>
  <Product>
    <Ln.>7</Ln.>
    <PO>18_12_17-4-4</PO>
    <ProductCode>4-4-PCYB05L-58</ProductCode>
    <Description></Description>
    <Qty>1</Qty>
    <UnitPrice>0.000</UnitPrice>
    <Amount>0.00</Amount>
  </Product>
  <Product>
    <Ln.>8</Ln.>
    <PO>18_12_17-4-4</PO>
    <ProductCode>4-4-PCYB04L-28</ProductCode>
    <Description></Description>
    <Qty>1</Qty>
    <UnitPrice>0.000</UnitPrice>
    <Amount>0.00</Amount>
  </Product>
  <Product>
    <Ln.>9</Ln.>
    <PO>18_12_17-4-4</PO>
    <ProductCode>4-4-PCYB04R-38</ProductCode>
    <Description></Description>
    <Qty>1</Qty>
    <UnitPrice>0.000</UnitPrice>
    <Amount>0.00</Amount>
  </Product>
  <Product>
    <Ln.>10</Ln.>
    <PO>18_12_17-4-4</PO>
    <ProductCode>4-4-PCYB03R-33</ProductCode>
    <Description></Description>
    <Qty>1</Qty>
    <UnitPrice>0.000</UnitPrice>
    <Amount>0.00</Amount>
  </Product>
  <Product>
    <Ln.>11</Ln.>
    <PO>18_12_17-4-4</PO>
    <ProductCode>4-4-PCYB02R-18</ProductCode>
    <Description></Description>
    <Qty>1</Qty>
    <UnitPrice>0.000</UnitPrice>
    <Amount>0.00</Amount>
  </Product>
  <Product>
    <Ln.>12</Ln.>
    <PO>18_12_17-4-4</PO>
    <ProductCode>4-4-PCYB12L-181</ProductCode>
    <Description></Description>
    <Qty>1</Qty>
    <UnitPrice>0.000</UnitPrice>
    <Amount>0.00</Amount>
  </Product>
  <Product>
    <Ln.>13</Ln.>
    <PO>18_12_17-4-4</PO>
    <ProductCode>4-4-PCYB02L-8</ProductCode>
    <Description></Description>
    <Qty>1</Qty>
    <UnitPrice>0.000</UnitPrice>
    <Amount>0.00</Amount>
  </Product>
  <Product>
    <Ln.>14</Ln.>
    <PO>18_12_17-4-4</PO>
    <ProductCode>4-4-PCYB01L-3</ProductCode>
    <Description></Description>
    <Qty>1</Qty>
    <UnitPrice>0.000</UnitPrice>
    <Amount>0.00</Amount>
  </Product>
  <Product>
    <Ln.>15</Ln.>
    <PO>18_12_17-4-4</PO>
    <ProductCode>4-4-PCYB01R-13</ProductCode>
    <Description></Description>
    <Qty>1</Qty>
    <UnitPrice>0.000</UnitPrice>
    <Amount>0.00</Amount>
  </Product>
  <Product>
    <Ln.>16</Ln.>
    <PO>18_12_17-4-4</PO>
    <ProductCode>4-4-PCYB06R-78</ProductCode>
    <Description></Description>
    <Qty>1</Qty>
    <UnitPrice>0.000</UnitPrice>
    <Amount>0.00</Amount>
  </Product>
  <Product>
    <Ln.>17</Ln.>
    <PO>18_12_17-4-4</PO>
    <ProductCode>4-4-PCYB06R-92</ProductCode>
    <Description></Description>
    <Qty>1</Qty>
    <UnitPrice>0.000</UnitPrice>
    <Amount>0.00</Amount>
  </Product>
  <Product>
    <Ln.>18</Ln.>
    <PO>18_12_17-4-4</PO>
    <ProductCode>4-4-PCYB13R-196</ProductCode>
    <Description></Description>
    <Qty>1</Qty>
    <UnitPrice>0.000</UnitPrice>
    <Amount>0.00</Amount>
  </Product>
  <Product>
    <Ln.>19</Ln.>
    <PO>18_12_17-4-4</PO>
    <ProductCode>4-4-PCYB11R-167</ProductCode>
    <Description></Description>
    <Qty>1</Qty>
    <UnitPrice>0.000</UnitPrice>
    <Amount>0.00</Amount>
  </Product>
  <Product>
    <Ln.>20</Ln.>
    <PO>18_12_17-4-4</PO>
    <ProductCode>4-4-PCYB11R-176</ProductCode>
    <Description></Description>
    <Qty>1</Qty>
    <UnitPrice>0.000</UnitPrice>
    <Amount>0.00</Amount>
  </Product>
  <Product>
    <Ln.>21</Ln.>
    <PO>18_12_17-4-4</PO>
    <ProductCode>4-4-PCYB10R-162</ProductCode>
    <Description></Description>
    <Qty>1</Qty>
    <UnitPrice>0.000</UnitPrice>
    <Amount>0.00</Amount>
  </Product>
  <Product>
    <Ln.>22</Ln.>
    <PO>18_12_17-4-4</PO>
    <ProductCode>4-4-PCYB10R-171</ProductCode>
    <Description></Description>
    <Qty>1</Qty>
    <UnitPrice>0.000</UnitPrice>
    <Amount>0.00</Amount>
  </Product>
  <Product>
    <Ln.>23</Ln.>
    <PO>18_12_17-4-4</PO>
    <ProductCode>4-4-PCYB10L-152</ProductCode>
    <Description></Description>
    <Qty>1</Qty>
    <UnitPrice>0.000</UnitPrice>
    <Amount>0.00</Amount>
  </Product>
  <Product>
    <Ln.>24</Ln.>
    <PO>18_12_17-4-4</PO>
    <ProductCode>4-4-PCYB10L-142</ProductCode>
    <Description></Description>
    <Qty>1</Qty>
    <UnitPrice>0.000</UnitPrice>
    <Amount>0.00</Amount>
  </Product>
  <Product>
    <Ln.>25</Ln.>
    <PO>18_12_17-4-4</PO>
    <ProductCode>4-4-PCYB03L-23</ProductCode>
    <Description></Description>
    <Qty>1</Qty>
    <UnitPrice>0.000</UnitPrice>
    <Amount>0.00</Amount>
  </Product>
</INVOICE>
