<?xml version="1.0" encoding="utf-8"?>
<INVOICE>
  <Product>
    <Ln.>1</Ln.>
    <PO>17_09_65-2-5</PO>
    <ProductCode>2-5-PCB10R-394</ProductCode>
    <Description></Description>
    <Qty>1</Qty>
    <UnitPrice>0.000</UnitPrice>
    <Amount>0.00</Amount>
  </Product>
  <Product>
    <Ln.>2</Ln.>
    <PO>17_09_65-2-5</PO>
    <ProductCode>2-5-PCYT02aR-1-568</ProductCode>
    <Description></Description>
    <Qty>1</Qty>
    <UnitPrice>0.000</UnitPrice>
    <Amount>0.00</Amount>
  </Product>
  <Product>
    <Ln.>3</Ln.>
    <PO>17_09_65-2-5</PO>
    <ProductCode>2-5-PCB10L-370</ProductCode>
    <Description></Description>
    <Qty>1</Qty>
    <UnitPrice>0.000</UnitPrice>
    <Amount>0.00</Amount>
  </Product>
  <Product>
    <Ln.>4</Ln.>
    <PO>17_09_65-2-5</PO>
    <ProductCode>2-5-PCB10L-364</ProductCode>
    <Description></Description>
    <Qty>1</Qty>
    <UnitPrice>0.000</UnitPrice>
    <Amount>0.00</Amount>
  </Product>
  <Product>
    <Ln.>5</Ln.>
    <PO>17_09_65-2-5</PO>
    <ProductCode>2-5-PCB10R-388</ProductCode>
    <Description></Description>
    <Qty>1</Qty>
    <UnitPrice>0.000</UnitPrice>
    <Amount>0.00</Amount>
  </Product>
  <Product>
    <Ln.>6</Ln.>
    <PO>17_09_65-2-5</PO>
    <ProductCode>2-5-PCB13L-4-184</ProductCode>
    <Description></Description>
    <Qty>1</Qty>
    <UnitPrice>0.000</UnitPrice>
    <Amount>0.00</Amount>
  </Product>
  <Product>
    <Ln.>7</Ln.>
    <PO>17_09_65-2-5</PO>
    <ProductCode>2-5-PCB13R-4-202</ProductCode>
    <Description></Description>
    <Qty>1</Qty>
    <UnitPrice>0.000</UnitPrice>
    <Amount>0.00</Amount>
  </Product>
  <Product>
    <Ln.>8</Ln.>
    <PO>17_09_65-2-5</PO>
    <ProductCode>2-5-PCB13L-2-118</ProductCode>
    <Description></Description>
    <Qty>1</Qty>
    <UnitPrice>0.000</UnitPrice>
    <Amount>0.00</Amount>
  </Product>
  <Product>
    <Ln.>9</Ln.>
    <PO>17_09_65-2-5</PO>
    <ProductCode>2-5-PCB13L-2-124</ProductCode>
    <Description></Description>
    <Qty>1</Qty>
    <UnitPrice>0.000</UnitPrice>
    <Amount>0.00</Amount>
  </Product>
  <Product>
    <Ln.>10</Ln.>
    <PO>17_09_65-2-5</PO>
    <ProductCode>2-5-PCB13L-4-190</ProductCode>
    <Description></Description>
    <Qty>1</Qty>
    <UnitPrice>0.000</UnitPrice>
    <Amount>0.00</Amount>
  </Product>
  <Product>
    <Ln.>11</Ln.>
    <PO>17_09_65-2-5</PO>
    <ProductCode>2-5-PCB13L-4-196</ProductCode>
    <Description></Description>
    <Qty>1</Qty>
    <UnitPrice>0.000</UnitPrice>
    <Amount>0.00</Amount>
  </Product>
  <Product>
    <Ln.>12</Ln.>
    <PO>17_09_65-2-5</PO>
    <ProductCode>2-5-PCB13L-3-148</ProductCode>
    <Description></Description>
    <Qty>1</Qty>
    <UnitPrice>0.000</UnitPrice>
    <Amount>0.00</Amount>
  </Product>
  <Product>
    <Ln.>13</Ln.>
    <PO>17_09_65-2-5</PO>
    <ProductCode>2-5-PCB13L-3-154</ProductCode>
    <Description></Description>
    <Qty>1</Qty>
    <UnitPrice>0.000</UnitPrice>
    <Amount>0.00</Amount>
  </Product>
  <Product>
    <Ln.>14</Ln.>
    <PO>17_09_65-2-5</PO>
    <ProductCode>2-5-PCYT02L-1-514</ProductCode>
    <Description></Description>
    <Qty>1</Qty>
    <UnitPrice>0.000</UnitPrice>
    <Amount>0.00</Amount>
  </Product>
  <Product>
    <Ln.>15</Ln.>
    <PO>17_09_65-2-5</PO>
    <ProductCode>2-5-PCB15L-405</ProductCode>
    <Description></Description>
    <Qty>1</Qty>
    <UnitPrice>0.000</UnitPrice>
    <Amount>0.00</Amount>
  </Product>
</INVOICE>
