<?xml version="1.0" encoding="utf-8"?>
<INVOICE>
  <Product>
    <Ln.>1</Ln.>
    <PO>18_12_19-11-5</PO>
    <ProductCode>11-5-PCB2L-23</ProductCode>
    <Description></Description>
    <Qty>1</Qty>
    <UnitPrice>0.000</UnitPrice>
    <Amount>0.00</Amount>
  </Product>
  <Product>
    <Ln.>2</Ln.>
    <PO>18_12_19-11-5</PO>
    <ProductCode>11-5-PCB3L-42</ProductCode>
    <Description></Description>
    <Qty>1</Qty>
    <UnitPrice>0.000</UnitPrice>
    <Amount>0.00</Amount>
  </Product>
  <Product>
    <Ln.>3</Ln.>
    <PO>18_12_19-11-5</PO>
    <ProductCode>11-5-PCB1R-61</ProductCode>
    <Description></Description>
    <Qty>1</Qty>
    <UnitPrice>0.000</UnitPrice>
    <Amount>0.00</Amount>
  </Product>
  <Product>
    <Ln.>4</Ln.>
    <PO>18_12_19-11-5</PO>
    <ProductCode>11-5-PCB3R-99</ProductCode>
    <Description></Description>
    <Qty>1</Qty>
    <UnitPrice>0.000</UnitPrice>
    <Amount>0.00</Amount>
  </Product>
  <Product>
    <Ln.>5</Ln.>
    <PO>18_12_19-11-5</PO>
    <ProductCode>11-5-PCB5L-137</ProductCode>
    <Description></Description>
    <Qty>1</Qty>
    <UnitPrice>0.000</UnitPrice>
    <Amount>0.00</Amount>
  </Product>
  <Product>
    <Ln.>6</Ln.>
    <PO>18_12_19-11-5</PO>
    <ProductCode>11-5-PCB4R-175</ProductCode>
    <Description></Description>
    <Qty>1</Qty>
    <UnitPrice>0.000</UnitPrice>
    <Amount>0.00</Amount>
  </Product>
  <Product>
    <Ln.>7</Ln.>
    <PO>18_12_19-11-5</PO>
    <ProductCode>11-5-PCB11R-289</ProductCode>
    <Description></Description>
    <Qty>1</Qty>
    <UnitPrice>0.000</UnitPrice>
    <Amount>0.00</Amount>
  </Product>
  <Product>
    <Ln.>8</Ln.>
    <PO>18_12_19-11-5</PO>
    <ProductCode>11-5-PCB9L-327</ProductCode>
    <Description></Description>
    <Qty>1</Qty>
    <UnitPrice>0.000</UnitPrice>
    <Amount>0.00</Amount>
  </Product>
  <Product>
    <Ln.>9</Ln.>
    <PO>18_12_19-11-5</PO>
    <ProductCode>11-5-PCB10L-346</ProductCode>
    <Description></Description>
    <Qty>1</Qty>
    <UnitPrice>0.000</UnitPrice>
    <Amount>0.00</Amount>
  </Product>
  <Product>
    <Ln.>10</Ln.>
    <PO>18_12_19-11-5</PO>
    <ProductCode>11-5-PCB8R-365</ProductCode>
    <Description></Description>
    <Qty>1</Qty>
    <UnitPrice>0.000</UnitPrice>
    <Amount>0.00</Amount>
  </Product>
  <Product>
    <Ln.>11</Ln.>
    <PO>18_12_19-11-5</PO>
    <ProductCode>11-5-PCB10R-403</ProductCode>
    <Description></Description>
    <Qty>1</Qty>
    <UnitPrice>0.000</UnitPrice>
    <Amount>0.00</Amount>
  </Product>
  <Product>
    <Ln.>12</Ln.>
    <PO>18_12_19-11-5</PO>
    <ProductCode>11-5-PCB13L-441</ProductCode>
    <Description></Description>
    <Qty>1</Qty>
    <UnitPrice>0.000</UnitPrice>
    <Amount>0.00</Amount>
  </Product>
  <Product>
    <Ln.>13</Ln.>
    <PO>18_12_19-11-5</PO>
    <ProductCode>11-5-PCB14L-460</ProductCode>
    <Description></Description>
    <Qty>1</Qty>
    <UnitPrice>0.000</UnitPrice>
    <Amount>0.00</Amount>
  </Product>
  <Product>
    <Ln.>14</Ln.>
    <PO>18_12_19-11-5</PO>
    <ProductCode>11-5-PCB15L-536</ProductCode>
    <Description></Description>
    <Qty>1</Qty>
    <UnitPrice>0.000</UnitPrice>
    <Amount>0.00</Amount>
  </Product>
  <Product>
    <Ln.>15</Ln.>
    <PO>18_12_19-11-5</PO>
    <ProductCode>11-5-PCB16L-555</ProductCode>
    <Description></Description>
    <Qty>1</Qty>
    <UnitPrice>0.000</UnitPrice>
    <Amount>0.00</Amount>
  </Product>
  <Product>
    <Ln.>16</Ln.>
    <PO>18_12_19-11-5</PO>
    <ProductCode>11-5-PCB19L-574</ProductCode>
    <Description></Description>
    <Qty>1</Qty>
    <UnitPrice>0.000</UnitPrice>
    <Amount>0.00</Amount>
  </Product>
  <Product>
    <Ln.>17</Ln.>
    <PO>18_12_19-11-5</PO>
    <ProductCode>11-5-PCB20L-593</ProductCode>
    <Description></Description>
    <Qty>1</Qty>
    <UnitPrice>0.000</UnitPrice>
    <Amount>0.00</Amount>
  </Product>
  <Product>
    <Ln.>18</Ln.>
    <PO>18_12_19-11-5</PO>
    <ProductCode>11-5-PCB16R-631</ProductCode>
    <Description></Description>
    <Qty>1</Qty>
    <UnitPrice>0.000</UnitPrice>
    <Amount>0.00</Amount>
  </Product>
  <Product>
    <Ln.>19</Ln.>
    <PO>18_12_19-11-5</PO>
    <ProductCode>11-5-PCB20R-669</ProductCode>
    <Description></Description>
    <Qty>1</Qty>
    <UnitPrice>0.000</UnitPrice>
    <Amount>0.00</Amount>
  </Product>
  <Product>
    <Ln.>20</Ln.>
    <PO>18_12_19-11-5</PO>
    <ProductCode>11-5-PCB17L-688</ProductCode>
    <Description></Description>
    <Qty>1</Qty>
    <UnitPrice>0.000</UnitPrice>
    <Amount>0.00</Amount>
  </Product>
  <Product>
    <Ln.>21</Ln.>
    <PO>18_12_19-11-5</PO>
    <ProductCode>11-5-PCB18L-707</ProductCode>
    <Description></Description>
    <Qty>1</Qty>
    <UnitPrice>0.000</UnitPrice>
    <Amount>0.00</Amount>
  </Product>
  <Product>
    <Ln.>22</Ln.>
    <PO>18_12_19-11-5</PO>
    <ProductCode>11-5-PCB18R-745</ProductCode>
    <Description></Description>
    <Qty>1</Qty>
    <UnitPrice>0.000</UnitPrice>
    <Amount>0.00</Amount>
  </Product>
</INVOICE>
